pypka/CHARMM36m/DataBaseT.crg
pypka/CHARMM36m/DataBaseT.siz
pypka/CHARMM36m/DataBaseT_template.crg
pypka/CHARMM36m/DataBaseT_template.siz
pypka/CHARMM36m/README.md
pypka/CHARMM36m/aa.rtp
pypka/CHARMM36m/extend_db.py
pypka/CHARMM36m/ffnonbonded.itp
pypka/CHARMM36m/sts/ASPtau1.st
pypka/CHARMM36m/sts/ASPtau2.st
pypka/CHARMM36m/sts/ASPtau3.st
pypka/CHARMM36m/sts/ASPtau4.st
pypka/CHARMM36m/sts/CTRtau1.st
pypka/CHARMM36m/sts/CTRtau2.st
pypka/CHARMM36m/sts/CTRtau3.st
pypka/CHARMM36m/sts/CTRtau4.st
pypka/CHARMM36m/sts/CYStau1.st
pypka/CHARMM36m/sts/CYStau2.st
pypka/CHARMM36m/sts/CYStau3.st
pypka/CHARMM36m/sts/GLUtau1.st
pypka/CHARMM36m/sts/GLUtau2.st
pypka/CHARMM36m/sts/GLUtau3.st
pypka/CHARMM36m/sts/GLUtau4.st
pypka/CHARMM36m/sts/HIStau1.st
pypka/CHARMM36m/sts/HIStau2.st
pypka/CHARMM36m/sts/LYStau1.st
pypka/CHARMM36m/sts/LYStau2.st
pypka/CHARMM36m/sts/LYStau3.st
pypka/CHARMM36m/sts/NTRtau1.st
pypka/CHARMM36m/sts/NTRtau2.st
pypka/CHARMM36m/sts/NTRtau3.st
pypka/CHARMM36m/sts/TYRtau1.st
pypka/CHARMM36m/sts/TYRtau2.st
pypka/CHARMM36m/sts_cphmd/ASPtau1.st
pypka/CHARMM36m/sts_cphmd/ASPtau2.st
pypka/CHARMM36m/sts_cphmd/ASPtau3.st
pypka/CHARMM36m/sts_cphmd/ASPtau4.st
pypka/CHARMM36m/sts_cphmd/CTRtau1.st
pypka/CHARMM36m/sts_cphmd/CTRtau2.st
pypka/CHARMM36m/sts_cphmd/CTRtau3.st
pypka/CHARMM36m/sts_cphmd/CTRtau4.st
pypka/CHARMM36m/sts_cphmd/CYStau1.st
pypka/CHARMM36m/sts_cphmd/CYStau2.st
pypka/CHARMM36m/sts_cphmd/CYStau3.st
pypka/CHARMM36m/sts_cphmd/GLUtau1.st
pypka/CHARMM36m/sts_cphmd/GLUtau2.st
pypka/CHARMM36m/sts_cphmd/GLUtau3.st
pypka/CHARMM36m/sts_cphmd/GLUtau4.st
pypka/CHARMM36m/sts_cphmd/HIStau1.st
pypka/CHARMM36m/sts_cphmd/HIStau2.st
pypka/CHARMM36m/sts_cphmd/LYStau1.st
pypka/CHARMM36m/sts_cphmd/LYStau2.st
pypka/CHARMM36m/sts_cphmd/LYStau3.st
pypka/CHARMM36m/sts_cphmd/NTRtau1.st
pypka/CHARMM36m/sts_cphmd/NTRtau2.st
pypka/CHARMM36m/sts_cphmd/NTRtau3.st
pypka/CHARMM36m/sts_cphmd/TYRtau1.st
pypka/CHARMM36m/sts_cphmd/TYRtau2.st
pypka/G54A7/DataBaseT.crg
pypka/G54A7/DataBaseT.siz
pypka-2.10.0.dist-info/LICENSE
pypka-2.10.0.dist-info/WHEEL
pypka-2.10.0.dist-info/METADATA
pypka-2.10.0.dist-info/RECORD
