Metadata-Version: 2.1
Name: pypka
Version: 2.10.0
Summary: A python module for flexible Poisson-Boltzmann based pKa calculations with proton tautomerism
Home-page: https://pypka.org
License: LGPLv3
Author: Pedro Reis
Author-email: pdreis@fc.ul.pt
Requires-Python: >=3.6.2,<4.0
Classifier: Development Status :: 5 - Production/Stable
Classifier: Intended Audience :: Science/Research
Classifier: License :: Other/Proprietary License
Classifier: Programming Language :: Python :: 3
Classifier: Programming Language :: Python :: 3.10
Classifier: Programming Language :: Python :: 3.7
Classifier: Programming Language :: Python :: 3.8
Classifier: Programming Language :: Python :: 3.9
Classifier: Topic :: Scientific/Engineering
Requires-Dist: delphi4py (==1.3.0)
Requires-Dist: numpy (>=1.19.0); python_version >= "3.6" and python_version < "3.7"
Requires-Dist: numpy (>=1.21.0); python_version >= "3.7" and python_version < "3.8"
Requires-Dist: numpy (>=1.23.0); python_version >= "3.8"
Requires-Dist: pdbmender (==0.6.1)
Requires-Dist: psutil
Requires-Dist: pytest (>=6.2.5)
Project-URL: Documentation, https://pypka.readthedocs.io/en/latest/
Project-URL: Repository, https://github.com/mms-fcul/PypKa
